hanzo_tools/__init__.py
hanzo_tools/lsp/__init__.py
hanzo_tools/lsp/lsp_tool.py
hanzo_tools_lsp-0.2.0.dist-info/METADATA
hanzo_tools_lsp-0.2.0.dist-info/WHEEL
hanzo_tools_lsp-0.2.0.dist-info/entry_points.txt
hanzo_tools_lsp-0.2.0.dist-info/top_level.txt
hanzo_tools_lsp-0.2.0.dist-info/RECORD
